idds/__init__.py
idds/monitor/__init__.py
idds/monitor/version.py
idds_monitor-2.0.9.data/data/monitor/data/conf.js
idds_monitor-2.0.9.data/data/monitor/data/conf.js.template
idds_monitor-2.0.9.data/data/monitor/data/dashboard.html
idds_monitor-2.0.9.data/data/monitor/data/detail_processing.html
idds_monitor-2.0.9.data/data/monitor/data/detail_request.html
idds_monitor-2.0.9.data/data/monitor/data/detail_transform.html
idds_monitor-2.0.9.data/data/monitor/data/processing.html
idds_monitor-2.0.9.data/data/monitor/data/transform.html
idds_monitor-2.0.9.data/data/monitor/data/backup/404.html
idds_monitor-2.0.9.data/data/monitor/data/backup/basic-table.html
idds_monitor-2.0.9.data/data/monitor/data/backup/blank.html
idds_monitor-2.0.9.data/data/monitor/data/backup/dashboard.html.backup
idds_monitor-2.0.9.data/data/monitor/data/backup/dashboard1.html
idds_monitor-2.0.9.data/data/monitor/data/backup/fontawesome.html
idds_monitor-2.0.9.data/data/monitor/data/backup/index.html.back
idds_monitor-2.0.9.data/data/monitor/data/backup/map-google.html
idds_monitor-2.0.9.data/data/monitor/data/backup/profile.html
idds_monitor-2.0.9.data/data/monitor/data/bootstrap/dist/.DS_Store
idds_monitor-2.0.9.data/data/monitor/data/bootstrap/dist/css/bootstrap-grid.css
idds_monitor-2.0.9.data/data/monitor/data/bootstrap/dist/css/bootstrap-grid.css.map
idds_monitor-2.0.9.data/data/monitor/data/bootstrap/dist/css/bootstrap-grid.min.css
idds_monitor-2.0.9.data/data/monitor/data/bootstrap/dist/css/bootstrap-grid.min.css.map
idds_monitor-2.0.9.data/data/monitor/data/bootstrap/dist/css/bootstrap-grid.rtl.css
idds_monitor-2.0.9.data/data/monitor/data/bootstrap/dist/css/bootstrap-grid.rtl.css.map
idds_monitor-2.0.9.data/data/monitor/data/bootstrap/dist/css/bootstrap-grid.rtl.min.css
idds_monitor-2.0.9.data/data/monitor/data/bootstrap/dist/css/bootstrap-grid.rtl.min.css.map
idds_monitor-2.0.9.data/data/monitor/data/bootstrap/dist/css/bootstrap-reboot.css
idds_monitor-2.0.9.dist-info/METADATA
idds_monitor-2.0.9.dist-info/WHEEL
idds_monitor-2.0.9.dist-info/top_level.txt
idds_monitor-2.0.9.dist-info/RECORD
